clabel/__init__.py
clabel/data_utils.py
clabel/demo.py
clabel/io.py
clabel/main.py
clabel/questions.py
clabel/styles.py
clabel-0.1.2.dist-info/entry_points.txt
clabel-0.1.2.dist-info/LICENSE
clabel-0.1.2.dist-info/WHEEL
clabel-0.1.2.dist-info/METADATA
clabel-0.1.2.dist-info/RECORD
